pihat/__init__.py
pihat/eeprom/__init__.py
pihat/eeprom/cli.py
pihat/eeprom/constants.py
pihat/eeprom/crc.py
pihat/eeprom/desc.py
pihat/eeprom/device.py
pihat/eeprom/exceptions.py
pihat/eeprom/file.py
pihat/eeprom/ideeprom0.dtbo
pihat/eeprom/ideeprom0.dts
pihat/eeprom/ideeprom1.dtbo
pihat/eeprom/ideeprom1.dts
pihat/eeprom/ideeprom99.dtbo
pihat/eeprom/ideeprom99.dts
pihat/eeprom/layout.py
pihat-0.0.6.dist-info/METADATA
pihat-0.0.6.dist-info/WHEEL
pihat-0.0.6.dist-info/entry_points.txt
pihat-0.0.6.dist-info/top_level.txt
pihat-0.0.6.dist-info/RECORD
